cheesecloth-0.2.2.dist-info/METADATA
cheesecloth-0.2.2.dist-info/WHEEL
cheesecloth-0.2.2.dist-info/entry_points.txt
cheesecloth/cli_entry.py
cheesecloth/py.typed
cheesecloth/tokenized_metrics.py
cheesecloth/data.py
cheesecloth/__init__.pyi
cheesecloth/__init__.py
cheesecloth/cli.py
cheesecloth/cheesecloth.cpython-311-x86_64-linux-gnu.so
cheesecloth-0.2.2.dist-info/RECORD
