Metadata-Version: 2.4
Name: cheesecloth
Version: 0.2.2
Classifier: Programming Language :: Rust
Classifier: Programming Language :: Python :: Implementation :: CPython
Classifier: Programming Language :: Python :: Implementation :: PyPy
Classifier: Development Status :: 3 - Alpha
Classifier: Intended Audience :: Science/Research
Classifier: Intended Audience :: Developers
Classifier: License :: OSI Approved :: MIT License
Classifier: Operating System :: OS Independent
Classifier: Programming Language :: Python
Classifier: Programming Language :: Python :: 3
Classifier: Programming Language :: Python :: 3.10
Classifier: Programming Language :: Python :: 3.11
Classifier: Programming Language :: Python :: 3.12
Classifier: Programming Language :: Python :: 3.13
Classifier: Topic :: Software Development :: Libraries :: Python Modules
Classifier: Topic :: Scientific/Engineering :: Information Analysis
Classifier: Topic :: Scientific/Engineering :: Artificial Intelligence
Classifier: Topic :: Utilities
Requires-Dist: datasets>=3.1.0
Requires-Dist: tokenizers>=0.21.0
Requires-Dist: tqdm>=4.67.1
Requires-Dist: pytest ; extra == 'tests'
Provides-Extra: tests
Summary: High-performance text metrics and filtering for large-scale corpora and pretrain curation
Keywords: alea,llm,data,cheesecloth,kl3m
Home-Page: https://aleainstitute.ai/
Author: ALEA Institute <hello@aleainstitute.ai>
Author-email: ALEA Institute <hello@aleainstitute.ai>
License: MIT
Requires-Python: >=3.8
Project-URL: Source Code, https://github.com/alea-institute/cheesecloth
